[{"__type__":"cc.AudioClip","_name":"spawn","_native":".mp3"},{"__type__":"cc.SpriteFrame","content":{"name":"7","texture":"f94T715rxGwYVIYEwNCulR","rect":[11,36,136,87],"offset":[-1,0.5],"originalSize":[160,160],"capInsets":[0,0,0,0]}},{"__type__":"cc.SpriteFrame","content":{"name":"Text_TLon","texture":"2eARXXrjlFL6g6Krw2rqEY","rect":[124,43,505,148],"offset":[5.5,-20.5],"originalSize":[742,193],"capInsets":[0,0,0,0]}},{"__type__":"cc.SpriteFrame","content":{"name":"BG","texture":"4fwFnhoHhFlqYSs8Zp95LT","rect":[0,0,800,480],"offset":[0,0],"originalSize":[800,480],"capInsets":[0,0,0,0]}},{"__type__":"cc.AudioClip","_name":"death","_native":".mp3"},{"__type__":"cc.AudioClip","_name":"shot","_native":".mp3"},{"__type__":"cc.SpriteFrame","content":{"name":"2","texture":"26i+sIDvRInpPU9gNJAkji","rect":[24,32,152,122],"offset":[0,7],"originalSize":[200,200],"capInsets":[0,0,0,0]}},{"__type__":"cc.SpriteFrame","content":{"name":"6","texture":"93Z9ZAel9LuYJkS7Sy/dqi","rect":[17,27,126,107],"offset":[0,-0.5],"originalSize":[160,160],"capInsets":[0,0,0,0]}},{"__type__":"cc.SpriteFrame","content":{"name":"4","texture":"b1HRQ4NeBLtJp1HPxwJyuU","rect":[23,18,154,136],"offset":[0,14],"originalSize":[200,200],"capInsets":[0,0,0,0]}},{"__type__":"cc.SpriteFrame","content":{"name":"R","texture":"a242KsaV5H5ZHY5Bog4hcl","rect":[24,16,152,164],"offset":[0,2],"originalSize":[200,200],"capInsets":[0,0,0,0]}},[{"__type__":"cc.Prefab","_name":"SymbolPrefab","data":{"__id__":1}},{"__type__":"cc.Node","_name":"SymbolPrefab","_children":[{"__id__":2},{"__id__":3}],"_level":1,"_components":[{"__type__":"bb9ef5r4lRFqJcW+ymuvU9X","node":{"__id__":1},"staticSymbol":{"__id__":2},"label":{"__id__":5},"cover":{"__id__":3},"symbols":[{"__uuid__":"61eTlkH+9CVoYgOUS6kgou"},{"__uuid__":"f8fKMXBhFHxZg5tvPDfL30"},{"__uuid__":"79mfWg+xZP0IQKe1wdL5E6"},{"__uuid__":"ed6hHxQStGsbvtjd/Aa1Nt"},{"__uuid__":"ccZSwP4bZLK7pcMjaAtun2"},{"__uuid__":"6bEGsSfxJL3ajYaj235nw+"},{"__uuid__":"3ct2feJD9NZbu6mpBGylCP"},{"__uuid__":"efEJ/GJDVLebNMZI+PZzuI"},{"__uuid__":"beEzxWT4hJZY6PI97by3fS"},{"__uuid__":"f5K5qBSARHOrvkSvzNKDsq"},{"__uuid__":"e3XSLgJ8BBd66cyUj1fLQ/"},{"__uuid__":"ed6hHxQStGsbvtjd/Aa1Nt"},{"__uuid__":"84ja5QTylOA4ZHU8qjT+56"}]},{"__type__":"cc.Button","node":{"__id__":1},"clickEvents":[{"__type__":"cc.ClickEvent","target":{"__id__":1},"_componentId":"bb9ef5r4lRFqJcW+ymuvU9X","handler":"onClick","customEventData":"1"}],"_N$target":{"__id__":1}}],"_prefab":{"__type__":"cc.PrefabInfo","root":{"__id__":1},"asset":{"__uuid__":"8fiLQVRXhAgbZZW/yKOtQ4"},"fileId":"26qelpOIhIMpp7yyIo0ELq"},"_contentSize":{"__type__":"cc.Size","width":100,"height":100}},{"__type__":"cc.Node","_name":"Symbol","_parent":{"__id__":1},"_level":4,"_components":[{"__type__":"cc.Sprite","node":{"__id__":2},"_materials":[{"__uuid__":"ecpdLyjvZBwrvm+cedCcQy"}],"_spriteFrame":{"__uuid__":"61eTlkH+9CVoYgOUS6kgou"},"_sizeMode":0}],"_prefab":{"__type__":"cc.PrefabInfo","root":{"__id__":1},"asset":{"__uuid__":"8fiLQVRXhAgbZZW/yKOtQ4"},"fileId":"564dp8ZsdPAr3LNcoOkcOL"},"_contentSize":{"__type__":"cc.Size","width":100,"height":100}},{"__type__":"cc.Node","_name":"Cover","_parent":{"__id__":1},"_children":[{"__id__":4}],"_level":2,"_components":[{"__type__":"cc.Sprite","node":{"__id__":3},"_materials":[{"__uuid__":"ecpdLyjvZBwrvm+cedCcQy"}],"_spriteFrame":{"__uuid__":"a2MjXRFdtLlYQ5ouAFv/+R"},"_sizeMode":0}],"_prefab":{"__type__":"cc.PrefabInfo","root":{"__id__":1},"asset":{"__uuid__":"8fiLQVRXhAgbZZW/yKOtQ4"},"fileId":"2fXYqqUrpOxIgFjDcLvH5b"},"_color":{"__type__":"cc.Color","r":231,"g":135,"b":12},"_contentSize":{"__type__":"cc.Size","width":100,"height":100}},{"__type__":"cc.Node","_name":"Label","_parent":{"__id__":3},"_level":3,"_components":[{"__id__":5}],"_prefab":{"__type__":"cc.PrefabInfo","root":{"__id__":1},"asset":{"__uuid__":"8fiLQVRXhAgbZZW/yKOtQ4"},"fileId":"18hMOs5kdJ8bSnSN+dmP4R"},"_contentSize":{"__type__":"cc.Size","width":33.36,"height":50.4}},{"__type__":"cc.Label","node":{"__id__":4},"_materials":[{"__uuid__":"ecpdLyjvZBwrvm+cedCcQy"}],"_useOriginalSize":false,"_string":"\r1","_N$string":"\r1","_N$horizontalAlign":1,"_N$verticalAlign":1}],{"__type__":"cc.SpriteFrame","content":{"name":"default_sprite_splash","texture":"02delMVqdBD70a/HSD99FK","rect":[0,0,2,2],"offset":[0,0],"originalSize":[2,2],"capInsets":[0,0,0,0]}},{"__type__":"cc.AudioClip","_name":"music","_native":".mp3"},{"__type__":"cc.SpriteFrame","content":{"name":"9","texture":"b4N/qeAitKyL+hxYtdJESm","rect":[38,21,84,71],"offset":[0,0.5],"originalSize":[160,114],"capInsets":[0,0,0,0]}},[{"__type__":"cc.SceneAsset","_name":"Game","scene":{"__id__":1},"asyncLoadAssets":null},{"__type__":"cc.Scene","_name":"New Node","_children":[{"__id__":2}],"_active":false,"_anchorPoint":{"__type__":"cc.Vec2"},"autoReleaseAssets":false},{"__type__":"cc.Node","_name":"Canvas","_parent":{"__id__":1},"_children":[{"__id__":3},{"__id__":4},{"__id__":20}],"_level":1,"_components":[{"__type__":"cc.Canvas","node":{"__id__":2}}],"_contentSize":{"__type__":"cc.Size","width":960,"height":640},"_position":{"__type__":"cc.Vec3","x":480,"y":320},"_id":"85PzLSAzlIN7bxM0w9MlQo"},{"__type__":"cc.Node","_name":"Main Camera","_parent":{"__id__":2},"_level":2,"_components":[{"__type__":"cc.Camera","node":{"__id__":3},"_clearFlags":7,"_depth":-1}],"_position":{"__type__":"cc.Vec3","z":353.338364744051}},{"__type__":"cc.Node","_name":"Game","_parent":{"__id__":2},"_children":[{"__id__":5},{"__id__":6},{"__id__":8},{"__id__":13},{"__id__":18}],"_level":2,"_components":[{"__type__":"ffe9cnPap9OkbmNjcEe35Aj","node":{"__id__":4},"scoreLabel":{"__id__":19},"winGamePanel":{"__id__":8},"loseGamePanel":{"__id__":13},"tableGame":{"__id__":6},"score":100,"startButton":{"__id__":18}},{"__type__":"5a92b7g85dHyqz0g1Sm0jBA","node":{"__id__":4},"breakAudio":{"__uuid__":"c5ZuWTFlZFMrludL1lo2aF"},"deathAudio":{"__uuid__":"5dFzv5FDVPGYXgKbFojiUc"},"musicAudio":{"__uuid__":"baNLLfY+dAj4shoRxU3gWK"},"shotAudio":{"__uuid__":"609CY05eFDqLNAHO7ZK/aB"},"spawnAudio":{"__uuid__":"086z5C+aNFro02U4hm6quH"}}]},{"__type__":"cc.Node","_name":"BG","_parent":{"__id__":4},"_level":3,"_components":[{"__type__":"cc.Sprite","node":{"__id__":5},"_materials":[{"__uuid__":"ecpdLyjvZBwrvm+cedCcQy"}],"_spriteFrame":{"__uuid__":"47WE2yZaFHnpJtDRM8fkpj"},"_sizeMode":0}],"_contentSize":{"__type__":"cc.Size","width":1280,"height":940}},{"__type__":"cc.Node","_name":"Table","_parent":{"__id__":4},"_children":[{"__id__":7}],"_level":3,"_components":[{"__type__":"de752dfnPhBBKD/x/FNIDFt","node":{"__id__":6},"table":{"__id__":7},"symbolPrefab":{"__uuid__":"8fiLQVRXhAgbZZW/yKOtQ4"},"spawnCount":20,"delayTime":1,"numberOfCol":5,"numberOfRow":4}],"_contentSize":{"__type__":"cc.Size","width":800,"height":640}},{"__type__":"cc.Node","_name":"Table","_parent":{"__id__":6},"_level":4,"_components":[{"__type__":"cc.Sprite","node":{"__id__":7},"_enabled":false,"_materials":[{"__uuid__":"ecpdLyjvZBwrvm+cedCcQy"}],"_spriteFrame":{"__uuid__":"47WE2yZaFHnpJtDRM8fkpj"},"_sizeMode":0}]},{"__type__":"cc.Node","_name":"WinGame","_parent":{"__id__":4},"_children":[{"__id__":9},{"__id__":10},{"__id__":11},{"__id__":12}],"_active":false,"_level":3,"_components":[{"__type__":"fffc3StzP5CqqurqKoIbCr1","node":{"__id__":8},"buttonPlay":{"__id__":12}}],"_contentSize":{"__type__":"cc.Size","width":960,"height":640}},{"__type__":"cc.Node","_name":"Frame_BigWin_half","_parent":{"__id__":8},"_level":4,"_components":[{"__type__":"cc.Sprite","node":{"__id__":9},"_materials":[{"__uuid__":"ecpdLyjvZBwrvm+cedCcQy"}],"_spriteFrame":{"__uuid__":"f12SthjrdHapGFiZCFp/zo"},"_sizeMode":0}],"_contentSize":{"__type__":"cc.Size","width":400,"height":200},"_anchorPoint":{"__type__":"cc.Vec2","x":0.41271,"y":0.5},"_position":{"__type__":"cc.Vec3","x":-230,"y":150}},{"__type__":"cc.Node","_name":"Frame_BigWin_half","_parent":{"__id__":8},"_level":4,"_components":[{"__type__":"cc.Sprite","node":{"__id__":10},"_materials":[{"__uuid__":"ecpdLyjvZBwrvm+cedCcQy"}],"_spriteFrame":{"__uuid__":"f12SthjrdHapGFiZCFp/zo"},"_sizeMode":0}],"_contentSize":{"__type__":"cc.Size","width":400,"height":200},"_position":{"__type__":"cc.Vec3","x":200,"y":150},"_scale":{"__type__":"cc.Vec3","x":-1,"y":1,"z":1}},{"__type__":"cc.Node","_name":"Text_TLon","_parent":{"__id__":8},"_level":4,"_components":[{"__type__":"cc.Sprite","node":{"__id__":11},"_materials":[{"__uuid__":"ecpdLyjvZBwrvm+cedCcQy"}],"_spriteFrame":{"__uuid__":"40QlgiME9MF6u6HR1WSrWv"}}],"_contentSize":{"__type__":"cc.Size","width":505,"height":148},"_position":{"__type__":"cc.Vec3","y":150}},{"__type__":"cc.Node","_name":"RestartButton","_parent":{"__id__":8},"_level":4,"_components":[{"__type__":"cc.Sprite","node":{"__id__":12},"_materials":[{"__uuid__":"ecpdLyjvZBwrvm+cedCcQy"}],"_spriteFrame":{"__uuid__":"c27fWPk1pCx5t6Gny0R6pD"},"_sizeMode":0},{"__type__":"cc.Button","node":{"__id__":12},"clickEvents":[{"__type__":"cc.ClickEvent","target":{"__id__":8},"_componentId":"fffc3StzP5CqqurqKoIbCr1","handler":"onClick"}]}],"_contentSize":{"__type__":"cc.Size","width":250,"height":250},"_position":{"__type__":"cc.Vec3","y":-200}},{"__type__":"cc.Node","_name":"\bLoseGame","_parent":{"__id__":4},"_children":[{"__id__":14},{"__id__":15},{"__id__":16},{"__id__":17}],"_active":false,"_level":3,"_components":[{"__type__":"fffc3StzP5CqqurqKoIbCr1","node":{"__id__":13},"buttonPlay":{"__id__":16}}],"_contentSize":{"__type__":"cc.Size","width":960,"height":640}},{"__type__":"cc.Node","_name":"Frame_BigWin_half","_parent":{"__id__":13},"_level":4,"_components":[{"__type__":"cc.Sprite","node":{"__id__":14},"_materials":[{"__uuid__":"ecpdLyjvZBwrvm+cedCcQy"}],"_spriteFrame":{"__uuid__":"f12SthjrdHapGFiZCFp/zo"},"_sizeMode":0}],"_contentSize":{"__type__":"cc.Size","width":400,"height":200},"_anchorPoint":{"__type__":"cc.Vec2","x":0.41271,"y":0.5},"_position":{"__type__":"cc.Vec3","x":-230,"y":150}},{"__type__":"cc.Node","_name":"Frame_BigWin_half","_parent":{"__id__":13},"_level":4,"_components":[{"__type__":"cc.Sprite","node":{"__id__":15},"_materials":[{"__uuid__":"ecpdLyjvZBwrvm+cedCcQy"}],"_spriteFrame":{"__uuid__":"f12SthjrdHapGFiZCFp/zo"},"_sizeMode":0}],"_contentSize":{"__type__":"cc.Size","width":400,"height":200},"_position":{"__type__":"cc.Vec3","x":200,"y":150},"_scale":{"__type__":"cc.Vec3","x":-1,"y":1,"z":1}},{"__type__":"cc.Node","_name":"RestartButton","_parent":{"__id__":13},"_level":4,"_components":[{"__type__":"cc.Sprite","node":{"__id__":16},"_materials":[{"__uuid__":"ecpdLyjvZBwrvm+cedCcQy"}],"_spriteFrame":{"__uuid__":"c27fWPk1pCx5t6Gny0R6pD"},"_sizeMode":0},{"__type__":"cc.Button","node":{"__id__":16},"clickEvents":[{"__type__":"cc.ClickEvent","target":{"__id__":13},"_componentId":"fffc3StzP5CqqurqKoIbCr1","handler":"onClick"}]}],"_contentSize":{"__type__":"cc.Size","width":250,"height":250},"_position":{"__type__":"cc.Vec3","y":-200}},{"__type__":"cc.Node","_name":"New Label","_parent":{"__id__":13},"_level":4,"_components":[{"__type__":"cc.Label","node":{"__id__":17},"_materials":[{"__uuid__":"ecpdLyjvZBwrvm+cedCcQy"}],"_useOriginalSize":false,"_string":"\bThuaaa!!","_N$string":"\bThuaaa!!","_fontSize":100,"_lineHeight":80,"_N$horizontalAlign":1,"_N$verticalAlign":1}],"_color":{"__type__":"cc.Color","r":255},"_contentSize":{"__type__":"cc.Size","width":394.73,"height":100.8},"_position":{"__type__":"cc.Vec3","y":150}},{"__type__":"cc.Node","_name":"StartButton","_parent":{"__id__":4},"_level":3,"_components":[{"__type__":"cc.Sprite","node":{"__id__":18},"_materials":[{"__uuid__":"ecpdLyjvZBwrvm+cedCcQy"}],"_spriteFrame":{"__uuid__":"c27fWPk1pCx5t6Gny0R6pD"}},{"__type__":"cc.Button","node":{"__id__":18},"clickEvents":[{"__type__":"cc.ClickEvent","target":{"__id__":4},"_componentId":"ffe9cnPap9OkbmNjcEe35Aj","handler":"playGame"}],"_N$target":{"__id__":4}}],"_contentSize":{"__type__":"cc.Size","width":240,"height":223}},{"__type__":"cc.Label","node":{"__id__":20},"_materials":[{"__uuid__":"ecpdLyjvZBwrvm+cedCcQy"}],"_useOriginalSize":false,"_string":"Score: 0","_N$string":"Score: 0","_N$horizontalAlign":1,"_N$verticalAlign":1},{"__type__":"cc.Node","_name":"Score","_parent":{"__id__":2},"_level":2,"_components":[{"__id__":19}],"_color":{"__type__":"cc.Color","r":12,"g":3,"b":3},"_contentSize":{"__type__":"cc.Size","width":148.96,"height":50.4},"_position":{"__type__":"cc.Vec3","x":-380.869,"y":274.782}}],{"__type__":"cc.SpriteFrame","content":{"name":"LDK_Icon","texture":"b2DcL+tdtF7LQijKxZXY6I","rect":[14,5,240,223],"offset":[0.5,0],"originalSize":[267,233],"capInsets":[0,0,0,0]}},{"__type__":"cc.AudioClip","_name":"break","_native":".mp3"},{"__type__":"cc.SpriteFrame","content":{"name":"5","texture":"64MyLBXAZEH6UHSe8XODVC","rect":[22,28,156,127],"offset":[0,8.5],"originalSize":[200,200],"capInsets":[0,0,0,0]}},{"__type__":"cc.SpriteFrame","content":{"name":"K","texture":"f79aEQ7I5Ne4uEYmbUpGC9","rect":[22,35,156,123],"offset":[0,3.5],"originalSize":[200,200],"capInsets":[0,0,0,0]}},{"__type__":"cc.SpriteFrame","content":{"name":"Q","texture":"4388f5cNpAbagZeAjMWSJL","rect":[35,20,89,73],"offset":[-0.5,0.5],"originalSize":[160,114],"capInsets":[0,0,0,0]}},{"__type__":"cc.SpriteFrame","content":{"name":"8","texture":"49ys2kCpJBSbpIqbva8p70","rect":[36,21,87,71],"offset":[-0.5,0.5],"originalSize":[160,114],"capInsets":[0,0,0,0]}},{"__type__":"cc.SpriteFrame","content":{"name":"Frame_BigWin_half","texture":"bfy9kK1fZHIJZOM8G8iqt7","rect":[2,1,360,231],"offset":[1,0],"originalSize":[362,233],"capInsets":[0,0,0,0]}},{"__type__":"cc.SpriteFrame","content":{"name":"A","texture":"37IurvVktE0pz9NOK93qHh","rect":[16,12,168,178],"offset":[0,-1],"originalSize":[200,200],"capInsets":[0,0,0,0]}},{"__type__":"cc.SpriteFrame","content":{"name":"3","texture":"caMEzqy8pLR7MADelGpG/k","rect":[23,14,154,140],"offset":[0,16],"originalSize":[200,200],"capInsets":[0,0,0,0]}}]